Metadata-Version: 2.1
Name: prependnewline
Version: 1.2
Summary: UNKNOWN
Home-page: https://gitlab.com/ayblaq/prependnewline
Author: Ayobami Adewale
Author-email: ayblaq@gmail.com
License: MIT License
Keywords: markdown prepend list with newline
Platform: UNKNOWN
Classifier: Programming Language :: Python
Classifier: Intended Audience :: Developers
Classifier: License :: OSI Approved :: MIT License
Classifier: Operating System :: OS Independent
Requires-Python: >=3.0
